sciextractai/__init__.py
sciextractai/main.py
sciextractai/prompts.py
sciextractai-2025.12.21153118.dist-info/METADATA
sciextractai-2025.12.21153118.dist-info/WHEEL
sciextractai-2025.12.21153118.dist-info/top_level.txt
sciextractai-2025.12.21153118.dist-info/RECORD
