Metadata-Version: 2.4
Name: sciextractai
Version: 2025.12.21153118
Summary: A new package designed to revolutionize scientific research by enabling precise extraction and structuring of key insights from complex scientific texts. This tool focuses on domains like attoscience,
Author-email: sciextractai <hi@eugene.plus>
License: MIT
Project-URL: Homepage, https://github.com/chigwell/sciextractai
Requires-Python: >=3.9
Requires-Dist: langchain-llm7>=0.0.0
Requires-Dist: llmatch-messages>=0.0.0
Requires-Dist: langchain-core>=0.3.0
